eqi_utils/__init__.py
eqi_utils/_version.py
eqi_utils/admin/__init__.py
eqi_utils/admin/csv_to_parquet.py
eqi_utils/admin/sample_jobs.py
eqi_utils/config/__init__.py
eqi_utils/config/config.py
eqi_utils/config/keys.py
eqi_utils/data/__init__.py
eqi_utils/data/bundle.py
eqi_utils/data/dbview.py
eqi_utils/data/s3.py
eqi_utils/data/utils.py
eqi_utils/data/view.py
eqi_utils/utils/ResourceUtils.py
eqi_utils/utils/__init__.py
eqi_utils-1.0.3.dist-info/METADATA
eqi_utils-1.0.3.dist-info/RECORD
eqi_utils-1.0.3.dist-info/WHEEL
eqi_utils-1.0.3.dist-info/top_level.txt
tests/__init__.py
tests/test_utilities_int.py
