Metadata-Version: 2.1
Name: eqi-utils
Version: 1.0.3
Summary: Common utilities for EQI project.
Home-page: https://github.com/jinzha098718/eqi-utilities
Author: Jinpeng Zhang
Author-email: jinzha098718@gmail.com
License: MIT
Platform: UNKNOWN
Classifier: Programming Language :: Python :: 3.6
Classifier: License :: OSI Approved :: MIT License
Classifier: Operating System :: OS Independent
Requires-Dist: boto3 (>=1.7.45)
Requires-Dist: pandas (>=0.23.1)
Requires-Dist: botocore (>=1.10.45)
Requires-Dist: pyyaml (>=3.12)
Requires-Dist: cx-Oracle (>=6.0b2)
Requires-Dist: sqlalchemy (>=1.2.8)
Requires-Dist: pyarrow (>=0.9.0)
Requires-Dist: fastparquet (>=0.1.5)
